.DS_Store
cvmblaster/__init__.py
cvmblaster/blaster.py
cvmblaster-0.6.1.dist-info/METADATA
cvmblaster-0.6.1.dist-info/WHEEL
cvmblaster-0.6.1.dist-info/top_level.txt
cvmblaster-0.6.1.dist-info/RECORD
